mlbull/__init__.py
mlbull/doc_router.py
mlbull/exceptions.py
mlbull/generate_router.py
mlbull/log_routes.py
mlbull/make_requirements.py
mlbull/notebooks.py
mlbull/precomputed.py
mlbull/print_logger.py
mlbull/streamlit.py
mlbull/utils.py
mlbull_dummies/__init__.py
mlbull-1.0.0.dist-info/LICENSE
mlbull-1.0.0.dist-info/METADATA
mlbull-1.0.0.dist-info/WHEEL
mlbull-1.0.0.dist-info/RECORD
